{
  "$schema": "https://developer.microsoft.com/json-schemas/fabric/item/report/definition/visualContainer/2.10.0/schema.json",
  "name": "cd99ba9700b916ca9b78",
  "position": {
    "x": 1529.6848860085076,
    "y": 0,
    "z": 1000,
    "height": 69.155002592016587,
    "width": 183.618455158113,
    "tabOrder": 1000
  },
  "visual": {
    "visualType": "textbox",
    "objects": {
      "general": [
        {
          "properties": {
            "paragraphs": [
              {
                "textRuns": [
                  {
                    "value": "Tiến độ:",
                    "textStyle": {
                      "fontWeight": "bold",
                      "fontSize": "24pt"
                    }
                  }
                ],
                "horizontalTextAlignment": "center"
              }
            ]
          }
        }
      ]
    },
    "visualContainerObjects": {
      "background": [
        {
          "properties": {
            "show": {
              "expr": {
                "Literal": {
                  "Value": "false"
                }
              }
            }
          }
        }
      ]
    },
    "drillFilterOtherVisuals": true
  }
}