{
  "$schema": "https://developer.microsoft.com/json-schemas/fabric/item/report/definition/visualContainer/2.10.0/schema.json",
  "name": "b5c9cf632145e2a8cb8f",
  "position": {
    "x": 231.42857142857142,
    "y": 103.74384236453201,
    "z": 4000,
    "height": 109.06403940886699,
    "width": 221.67487684729065,
    "tabOrder": 3000
  },
  "visual": {
    "visualType": "card",
    "query": {
      "queryState": {
        "Values": {
          "projections": [
            {
              "field": {
                "Measure": {
                  "Expression": {
                    "SourceRef": {
                      "Entity": "Table"
                    }
                  },
                  "Property": "Total công việc hoàn thành"
                }
              },
              "queryRef": "Table.Total công việc hoàn thành",
              "nativeQueryRef": "Total công việc hoàn thành"
            }
          ]
        }
      },
      "sortDefinition": {
        "sort": [
          {
            "field": {
              "Measure": {
                "Expression": {
                  "SourceRef": {
                    "Entity": "Table"
                  }
                },
                "Property": "Total công việc hoàn thành"
              }
            },
            "direction": "Descending"
          }
        ],
        "isDefaultSort": true
      }
    },
    "objects": {
      "labels": [
        {
          "properties": {
            "fontSize": {
              "expr": {
                "Literal": {
                  "Value": "16D"
                }
              }
            },
            "fontFamily": {
              "expr": {
                "Literal": {
                  "Value": "'''Segoe UI'', wf_segoe-ui_normal, helvetica, arial, sans-serif'"
                }
              }
            }
          }
        }
      ],
      "categoryLabels": [
        {
          "properties": {
            "show": {
              "expr": {
                "Literal": {
                  "Value": "false"
                }
              }
            }
          }
        }
      ]
    },
    "visualContainerObjects": {
      "title": [
        {
          "properties": {
            "show": {
              "expr": {
                "Literal": {
                  "Value": "true"
                }
              }
            },
            "text": {
              "expr": {
                "Literal": {
                  "Value": "'Công việc hoàn thành'"
                }
              }
            },
            "fontFamily": {
              "expr": {
                "Literal": {
                  "Value": "'''Segoe UI'', wf_segoe-ui_normal, helvetica, arial, sans-serif'"
                }
              }
            },
            "fontSize": {
              "expr": {
                "Literal": {
                  "Value": "10D"
                }
              }
            },
            "alignment": {
              "expr": {
                "Literal": {
                  "Value": "'center'"
                }
              }
            },
            "background": {
              "solid": {
                "color": {
                  "expr": {
                    "Literal": {
                      "Value": "'#C2DCF4'"
                    }
                  }
                }
              }
            }
          }
        }
      ],
      "border": [
        {
          "properties": {
            "show": {
              "expr": {
                "Literal": {
                  "Value": "true"
                }
              }
            },
            "color": {
              "solid": {
                "color": {
                  "expr": {
                    "ThemeDataColor": {
                      "ColorId": 0,
                      "Percent": -0.1
                    }
                  }
                }
              }
            }
          }
        }
      ]
    },
    "drillFilterOtherVisuals": true
  },
  "filterConfig": {
    "filters": [
      {
        "name": "e80174cd30f0ce0375f0",
        "ordinal": 0,
        "field": {
          "Measure": {
            "Expression": {
              "SourceRef": {
                "Entity": "Table"
              }
            },
            "Property": "Total công việc"
          }
        },
        "type": "Advanced",
        "howCreated": "User"
      },
      {
        "name": "f2616b022b46ff2f0057",
        "ordinal": 1,
        "field": {
          "Measure": {
            "Expression": {
              "SourceRef": {
                "Entity": "Table"
              }
            },
            "Property": "Total công việc hoàn thành"
          }
        },
        "type": "Advanced"
      },
      {
        "name": "bfff8d7748c276f0292b",
        "ordinal": 2,
        "field": {
          "Column": {
            "Expression": {
              "SourceRef": {
                "Entity": "Eoffice_TD"
              }
            },
            "Property": "parent_title"
          }
        },
        "type": "Categorical",
        "filter": {
          "Version": 2,
          "From": [
            {
              "Name": "e",
              "Entity": "Eoffice_TD",
              "Type": 0
            }
          ],
          "Where": [
            {
              "Condition": {
                "In": {
                  "Expressions": [
                    {
                      "Column": {
                        "Expression": {
                          "SourceRef": {
                            "Source": "e"
                          }
                        },
                        "Property": "parent_title"
                      }
                    }
                  ],
                  "Values": [
                    [
                      {
                        "Literal": {
                          "Value": "'2.2 QSB'"
                        }
                      }
                    ]
                  ]
                }
              }
            }
          ]
        },
        "howCreated": "User"
      }
    ],
    "filterSortOrder": "Custom"
  }
}