{
  "$schema": "https://developer.microsoft.com/json-schemas/fabric/item/report/definition/bookmarksMetadata/1.0.0/schema.json",
  "items": [
    {
      "name": "29316646f82864375139"
    },
    {
      "name": "6e114232810062de9a27"
    },
    {
      "name": "ee03f8e0cb41cc6eee01"
    },
    {
      "name": "b2415b8efe20ece5b225"
    },
    {
      "name": "e2aec7445cd1b3cccfef"
    },
    {
      "name": "c06f5ca282c42baf7f5a"
    },
    {
      "name": "514eaba10567cd6f5462"
    },
    {
      "name": "c17f06283ac07a85aff9"
    },
    {
      "name": "3894042af3ab3f3ce105"
    },
    {
      "name": "3c7eaf70b0e70db134d8"
    },
    {
      "name": "a9c3a3703eae9482553a"
    },
    {
      "name": "feff9f5ac3031b647e5f"
    },
    {
      "name": "0908204d8859b573aaae"
    },
    {
      "name": "6ec1aec76693c5d2b46e"
    },
    {
      "name": "cbebc9aa5eb722a3aa9b"
    },
    {
      "name": "26a88b36e5a72a7bc40f"
    },
    {
      "name": "dd95b42f9d8707141954"
    },
    {
      "name": "e1d8d55447e771c205af"
    },
    {
      "name": "34c66bb79d3c7f70d672"
    },
    {
      "name": "5be1488b4f91ebbe6a12"
    },
    {
      "name": "68896346cf7c7170ee27"
    },
    {
      "name": "16c2347a65fcfb90c383"
    },
    {
      "name": "55ea2ded44734b010a0f"
    },
    {
      "name": "44d8d9685db965ab933c"
    },
    {
      "name": "cc66b13b187866661d6f"
    },
    {
      "name": "d791e0f804a9db0a2228"
    }
  ]
}